{
    "fluentMethods": true,
    "relationships": [],
    "fields": [
        {
            "fieldName": "date",
            "fieldType": "ZonedDateTime",
            "fieldValidateRules": [
                "required"
            ]
        },
        {
            "fieldName": "reason",
            "fieldType": "StockCase",
            "fieldValues": "ADDED,REMOVED,DIED"
        },
        {
            "fieldName": "description",
            "fieldType": "String"
        },
        {
            "fieldName": "qty",
            "fieldType": "Integer",
            "fieldValidateRules": [
                "required"
            ]
        },
        {
            "fieldName": "tempVal",
            "fieldType": "Double",
            "fieldValidateRules": [
                "required"
            ]
        },
        {
            "fieldName": "timestamp",
            "fieldType": "Integer"
        }
    ],
    "changelogDate": "20180613100927",
    "entityTableName": "live_stock",
    "dto": "mapstruct",
    "pagination": "pagination",
    "service": "no",
    "jpaMetamodelFiltering": false,
    "angularJSSuffix": "mySuffix",
    "microserviceName": "pond"
}